{
    "url": "https://www.db.com/news/detail/20220908-a-statement-from-db-uk-ceo-on-the-passing-of-her-majesty-the-queen?language_id=1",
    "language": "EN",
    "article_type": "News",
    "publish_date": "September 8, 2022",
    "tags": [
        "Europe"
    ],
    "title": "A Statement from Deutsche Bank's UK CEO on the Passing Of Her Majesty The Queen",
    "body": "We are deeply saddened by the death of Her Majesty the Queen earlier today. I join colleagues around the world in mourning her passing and reflecting on her extraordinary lifetime of service to the UK and the wider Commonwealth.\nTiina Lee, Chief Executive of Deutsche Bank UK and Ireland",
    "number_of_ratings": 6,
    "rating": 5.0,
    "likes": 28
}